odoo10_addon_sale_automatic_workflow_payment_mode-10.0.1.0.3-py3.8-nspkg.pth
odoo/addons/sale_automatic_workflow_payment_mode/README.rst
odoo/addons/sale_automatic_workflow_payment_mode/__init__.py
odoo/addons/sale_automatic_workflow_payment_mode/__manifest__.py
odoo/addons/sale_automatic_workflow_payment_mode/data/automatic_workflow_data.xml
odoo/addons/sale_automatic_workflow_payment_mode/i18n/ca.po
odoo/addons/sale_automatic_workflow_payment_mode/i18n/de.po
odoo/addons/sale_automatic_workflow_payment_mode/i18n/el_GR.po
odoo/addons/sale_automatic_workflow_payment_mode/i18n/es.po
odoo/addons/sale_automatic_workflow_payment_mode/i18n/es_ES.po
odoo/addons/sale_automatic_workflow_payment_mode/i18n/es_VE.po
odoo/addons/sale_automatic_workflow_payment_mode/i18n/fi.po
odoo/addons/sale_automatic_workflow_payment_mode/i18n/fr.po
odoo/addons/sale_automatic_workflow_payment_mode/i18n/hr.po
odoo/addons/sale_automatic_workflow_payment_mode/i18n/hr_HR.po
odoo/addons/sale_automatic_workflow_payment_mode/i18n/hu.po
odoo/addons/sale_automatic_workflow_payment_mode/i18n/it.po
odoo/addons/sale_automatic_workflow_payment_mode/i18n/nl.po
odoo/addons/sale_automatic_workflow_payment_mode/i18n/nl_NL.po
odoo/addons/sale_automatic_workflow_payment_mode/i18n/pt.po
odoo/addons/sale_automatic_workflow_payment_mode/i18n/pt_BR.po
odoo/addons/sale_automatic_workflow_payment_mode/i18n/ro.po
odoo/addons/sale_automatic_workflow_payment_mode/i18n/sale_automatic_workflow_payment_mode.pot
odoo/addons/sale_automatic_workflow_payment_mode/i18n/sk.po
odoo/addons/sale_automatic_workflow_payment_mode/i18n/sl.po
odoo/addons/sale_automatic_workflow_payment_mode/i18n/tr.po
odoo/addons/sale_automatic_workflow_payment_mode/i18n/tr_TR.po
odoo/addons/sale_automatic_workflow_payment_mode/i18n/vi_VN.po
odoo/addons/sale_automatic_workflow_payment_mode/i18n/zh_CN.po
odoo/addons/sale_automatic_workflow_payment_mode/models/__init__.py
odoo/addons/sale_automatic_workflow_payment_mode/models/account_invoice.py
odoo10_addon_sale_automatic_workflow_payment_mode-10.0.1.0.3.dist-info/METADATA
odoo10_addon_sale_automatic_workflow_payment_mode-10.0.1.0.3.dist-info/WHEEL
odoo10_addon_sale_automatic_workflow_payment_mode-10.0.1.0.3.dist-info/namespace_packages.txt
odoo10_addon_sale_automatic_workflow_payment_mode-10.0.1.0.3.dist-info/top_level.txt
odoo10_addon_sale_automatic_workflow_payment_mode-10.0.1.0.3.dist-info/RECORD
